__init__.py
j2bfield.py
j2bfield-0.0.8.dist-info/METADATA
j2bfield-0.0.8.dist-info/WHEEL
j2bfield-0.0.8.dist-info/top_level.txt
j2bfield-0.0.8.dist-info/RECORD
