Metadata-Version: 2.1
Name: j2bfield
Version: 0.0.8
Summary: J field to B field
Author-email: Aheck <610993278@qq.com>
Project-URL: Homepage, https://github.com/pypa/sampleproject
Project-URL: Bug Tracker, https://github.com/pypa/sampleproject/issues
Classifier: Programming Language :: Python :: 3
Requires-Python: >=3.7
